dockupdater/__init__.py
dockupdater/dockupdater.py
dockupdater/helpers/__init__.py
dockupdater/helpers/helpers.py
dockupdater/lib/__init__.py
dockupdater/lib/config.py
dockupdater/lib/dockerclient.py
dockupdater/lib/logger.py
dockupdater/lib/notifiers.py
dockupdater/lib/scanner.py
dockupdater/templates/notification.j2
dockupdater/update/__init__.py
dockupdater/update/abstract.py
dockupdater/update/container.py
dockupdater/update/service.py
dockupdater-0.8.0.data/scripts/entrypoint
dockupdater-0.8.0.dist-info/LICENSE
dockupdater-0.8.0.dist-info/METADATA
dockupdater-0.8.0.dist-info/WHEEL
dockupdater-0.8.0.dist-info/top_level.txt
dockupdater-0.8.0.dist-info/RECORD
