Metadata-Version: 2.1
Name: dockupdater
Version: 0.8.0
Summary: Automatically keep your docker services and your docker containers up-to-date with the latest version
Home-page: https://dockupdater.dev
Maintainer: Mathieu Cantin
Maintainer-email: harcher81@gmail.com
License: MIT
Platform: UNKNOWN
Classifier: Programming Language :: Python
Classifier: Programming Language :: Python :: 3.6
Classifier: Programming Language :: Python :: 3.7
Requires-Python: >=3.6.2
Requires-Dist: docker (>=3.7.0)
Requires-Dist: apscheduler (>=3.5.3)
Requires-Dist: requests (>=2.21.0)
Requires-Dist: apprise (>=0.8.9)
Requires-Dist: jinja2 (>=2.10)
Requires-Dist: click (>=7.0)
